MANIFEST.in
setup.py
mkdocs_inspired/__init__.py
mkdocs_inspired/base.html
mkdocs_inspired/content.html
mkdocs_inspired/nav.html
mkdocs_inspired/toc.html
mkdocs_inspired.egg-info/PKG-INFO
mkdocs_inspired.egg-info/SOURCES.txt
mkdocs_inspired.egg-info/dependency_links.txt
mkdocs_inspired.egg-info/entry_points.txt
mkdocs_inspired.egg-info/not-zip-safe
mkdocs_inspired.egg-info/top_level.txt
mkdocs_inspired/bower_components/font-awesome/css/font-awesome.css
mkdocs_inspired/bower_components/font-awesome/css/font-awesome.min.css
mkdocs_inspired/bower_components/font-awesome/fonts/fontawesome-webfont.eot
mkdocs_inspired/bower_components/font-awesome/fonts/fontawesome-webfont.svg
mkdocs_inspired/bower_components/font-awesome/fonts/fontawesome-webfont.ttf
mkdocs_inspired/bower_components/font-awesome/fonts/fontawesome-webfont.woff
mkdocs_inspired/bower_components/jquery/dist/core.js
mkdocs_inspired/bower_components/jquery/dist/jquery.js
mkdocs_inspired/bower_components/jquery/dist/jquery.min.js
mkdocs_inspired/bower_components/jquery/dist/jquery.slim.js
mkdocs_inspired/bower_components/jquery/dist/jquery.slim.min.js
mkdocs_inspired/bower_components/jquery/external/sizzle/dist/sizzle.js
mkdocs_inspired/bower_components/jquery/external/sizzle/dist/sizzle.min.js
mkdocs_inspired/bower_components/jquery/src/ajax.js
mkdocs_inspired/bower_components/jquery/src/attributes.js
mkdocs_inspired/bower_components/jquery/src/callbacks.js
mkdocs_inspired/bower_components/jquery/src/core.js
mkdocs_inspired/bower_components/jquery/src/css.js
mkdocs_inspired/bower_components/jquery/src/data.js
mkdocs_inspired/bower_components/jquery/src/deferred.js
mkdocs_inspired/bower_components/jquery/src/deprecated.js
mkdocs_inspired/bower_components/jquery/src/dimensions.js
mkdocs_inspired/bower_components/jquery/src/effects.js
mkdocs_inspired/bower_components/jquery/src/event.js
mkdocs_inspired/bower_components/jquery/src/jquery.js
mkdocs_inspired/bower_components/jquery/src/manipulation.js
mkdocs_inspired/bower_components/jquery/src/offset.js
mkdocs_inspired/bower_components/jquery/src/queue.js
mkdocs_inspired/bower_components/jquery/src/selector-native.js
mkdocs_inspired/bower_components/jquery/src/selector-sizzle.js
